file_handler_dir/__init__.py
file_handler_dir/file_handler.py
src/__init__.py
src/main.py
list_to_tabs-1.2.2.dist-info/LICENSE
list_to_tabs-1.2.2.dist-info/METADATA
list_to_tabs-1.2.2.dist-info/WHEEL
list_to_tabs-1.2.2.dist-info/entry_points.txt
list_to_tabs-1.2.2.dist-info/top_level.txt
list_to_tabs-1.2.2.dist-info/RECORD
