Metadata-Version: 2.1
Name: list-to-tabs
Version: 1.2.2
Summary: A python package for converting newline files into konsole-tabs
Home-page: https://github.com/jackpots28/list_to_konsole-tabs
Author: Jack Sims
Author-email: jack.m.sims@protonmail.com
License: GPL
Classifier: Development Status :: 5 - Production/Stable
Classifier: Intended Audience :: Developers
Classifier: Intended Audience :: System Administrators
Classifier: Intended Audience :: Information Technology
Classifier: Environment :: Console
Classifier: License :: OSI Approved :: GNU General Public License (GPL)
Classifier: Operating System :: POSIX :: Linux
Classifier: Topic :: System :: Shells
Classifier: Topic :: Utilities
Classifier: Programming Language :: Python :: 3.11
License-File: LICENSE
Requires-Dist: argparse
Requires-Dist: setuptools
Requires-Dist: wheel
